g29py/__init__.py
g29py/g29.py
g29py/params.py
g29py-0.1.0.dist-info/LICENSE
g29py-0.1.0.dist-info/WHEEL
g29py-0.1.0.dist-info/METADATA
g29py-0.1.0.dist-info/RECORD
