Metadata-Version: 2.1
Name: g29py
Version: 0.1.0
Summary: python driver for g29 wheel/pedals
Author: sean pollock
Author-email: seanap@protonmail.com
Requires-Python: >=3.8,<4.0
Classifier: Programming Language :: Python :: 3
Classifier: Programming Language :: Python :: 3.8
Classifier: Programming Language :: Python :: 3.9
Classifier: Programming Language :: Python :: 3.10
Classifier: Programming Language :: Python :: 3.11
Requires-Dist: hid (==1.0.4)
